zerpy/__init__.py
zerpy/zerpy.py
zerpy-1.0.0.dist-info/LICENSE
zerpy-1.0.0.dist-info/METADATA
zerpy-1.0.0.dist-info/WHEEL
zerpy-1.0.0.dist-info/top_level.txt
zerpy-1.0.0.dist-info/RECORD
