Metadata-Version: 2.1
Name: zerpy
Version: 1.0.0
Summary: 🔗 Package Guide On https://github.com/MohamedLunar/zerpy
Home-page: https://github.com/MohamedLunar/zerpy
Author: MohamedLunar
Author-email: contact.mohamedlunardev@gmail.com
Classifier: Programming Language :: Python :: 3
Classifier: License :: OSI Approved :: MIT License
Classifier: Operating System :: OS Independent
Requires-Python: >=3.10
License-File: LICENSE
Requires-Dist: python-dotenv
